square_skill_api/__init__.py
square_skill_api/api/__init__.py
square_skill_api/api/routes/__init__.py
square_skill_api/api/routes/heartbeat.py
square_skill_api/api/routes/query.py
square_skill_api/api/routes/router.py
square_skill_api/core/__init__.py
square_skill_api/core/event_handlers.py
square_skill_api/core/messages.py
square_skill_api/models/__init__.py
square_skill_api/models/heartbeat.py
square_skill_api/models/prediction.py
square_skill_api/models/request.py
square_skill_api-0.0.47.dist-info/METADATA
square_skill_api-0.0.47.dist-info/WHEEL
square_skill_api-0.0.47.dist-info/top_level.txt
square_skill_api-0.0.47.dist-info/RECORD
