Metadata-Version: 2.1
Name: square-skill-api
Version: 0.0.47
Summary: UNKNOWN
Home-page: https://github.com/UKP-SQuARE/square-skill-api
Author: UKP
Author-email: baumgaertner@ukp.informatik.tu-darmstadt.de
License: MIT
Download-URL: https://github.com/UKP-SQuARE/square-skill-api/archive/refs/tags/v0.0.47.tar.gz
Platform: UNKNOWN
Requires-Dist: uvicorn >=0.15.0
Requires-Dist: fastapi >=0.65.2
Requires-Dist: pydantic <2.0
Requires-Dist: numpy >=1.21.3
Requires-Dist: square-elk-json-formatter ==0.0.3
